taqyeem/__init__.py
taqyeem/_base.py
taqyeem-0.0.1.dist-info/LICENSE
taqyeem-0.0.1.dist-info/METADATA
taqyeem-0.0.1.dist-info/WHEEL
taqyeem-0.0.1.dist-info/top_level.txt
taqyeem-0.0.1.dist-info/RECORD
