Metadata-Version: 2.1
Name: taqyeem
Version: 0.0.1
Summary: A python library for recording and reporting evaluation of ml models
Home-page: https://github.com/samehkamaleldin/taqyeem
Author: Sameh K. Mohamed
Author-email: sameh.kamaleldin@gmail.com
License: UNKNOWN
Keywords: evaluation logging ml
Platform: UNKNOWN
Requires-Python: >=3.6
Provides-Extra: dev
Requires-Dist: pytest ; extra == 'dev'
Requires-Dist: sphinx ; extra == 'dev'
Provides-Extra: test
Requires-Dist: pytest ; extra == 'test'
